<?xml version="1.0" encoding="utf-8"?>
<!DOCTYPE hibernate-mapping PUBLIC
        "-//Hibernate/Hibernate Mapping DTD//EN"
        "http://www.hibernate.org/dtd/hibernate-mapping-3.0.dtd">

<hibernate-mapping
    package="by.pvt.herzhot.pojos.other"
>
    <class
        name="Author"
        table="authors"
        schema="hibertest"
    >
        <id name="id" type="int" column="id">
            <generator class="native"/>
        </id>
        <property name="firstName"   column="first_name"/>
        <property name="lastName"    column="last_name" />
        <property name="email"       column="email"     />
        <property name="password"    column="password"  />
        <property name="accessLevel" column="access_lvl"/>

    </class>
</hibernate-mapping> 